[{"line":1,"uri":"file:src/test/resources/Features/Profile.feature","id":"shop-by-category-functionality","keyword":"Feature","name":"Shop by Category Functionality","description":"","elements":[{"start_timestamp":"2025-11-13T09:18:52.776Z","line":4,"id":"shop-by-category-functionality;user-landing-on-homepage","type":"scenario","keyword":"Scenario","name":"User Landing on HomePage","description":"","steps":[{"keyword":"Given ","line":5,"match":{"location":"com.stepDefinitionTestNG.Profile.the_user_is_on_the_apollo_homepage(java.lang.Integer)","arguments":[{"val":"247","offset":26}]},"name":"the user is on the Apollo 247 homepage","result":{"duration":16265525200,"status":"passed"}},{"keyword":"When ","line":6,"match":{"location":"com.stepDefinitionTestNG.Profile.the_user_clicks_on_health_monitors_under_shop_by_category()"},"name":"the user clicks on Health Monitors under Shop by Category","result":{"duration":15644123200,"status":"passed"}},{"keyword":"Then ","line":7,"match":{"location":"com.stepDefinitionTestNG.Profile.the_categories_page_should_be_displayed()"},"name":"the categories page should be displayed","result":{"duration":14439100,"status":"passed"}}]},{"start_timestamp":"2025-11-13T09:19:24.732Z","line":17,"id":"shop-by-category-functionality;user-landing-on-healthmonitors-page","type":"scenario","keyword":"Scenario","name":"user Landing on HealthMonitors Page","description":"","steps":[{"keyword":"Given ","line":18,"match":{"location":"com.stepDefinitionTestNG.Profile.the_user_is_on_health_monitors_page()"},"name":"the user is on Health Monitors Page","result":{"duration":3007402300,"status":"passed"}},{"keyword":"When ","line":19,"match":{"location":"com.stepDefinitionTestNG.Profile.the_user_clicks_on_apollo_products()"},"name":"the user clicks on Apollo products","result":{"duration":4158837700,"status":"passed"}},{"keyword":"And ","line":20,"match":{"location":"com.stepDefinitionTestNG.Profile.user_clicks_on_personal_care_products()"},"name":"user clicks on personal care products","result":{"duration":4178117200,"status":"passed"}},{"keyword":"And ","line":21,"match":{"location":"com.stepDefinitionTestNG.Profile.user_clicks_on_baby_care_prodcuts()"},"name":"user clicks on Baby care prodcuts","result":{"duration":5196981800,"status":"passed"}},{"keyword":"Then ","line":22,"match":{"location":"com.stepDefinitionTestNG.Profile.user_clicls_on_otc_products()"},"name":"user clicls on OTC products","result":{"duration":5185172900,"status":"passed"}}]},{"start_timestamp":"2025-11-13T09:19:46.466Z","line":24,"id":"shop-by-category-functionality;user-landing-on-nutritional-drinks-and-supplements-page","type":"scenario","keyword":"Scenario","name":"user Landing on Nutritional Drinks and Supplements page","description":"","steps":[{"keyword":"Given ","line":25,"match":{"location":"com.stepDefinitionTestNG.Profile.the_user_is_on_nutritional_drinks_and_supplements_page()"},"name":"the user is on Nutritional Drinks and Supplements page","result":{"duration":3012509100,"status":"passed"}},{"keyword":"When ","line":26,"match":{"location":"com.stepDefinitionTestNG.Profile.the_user_clicks_on_nutritional_drinks_and_supplements()"},"name":"the user clicks on Nutritional Drinks and Supplements","result":{"duration":4179657500,"status":"passed"}},{"keyword":"And ","line":27,"match":{"location":"com.stepDefinitionTestNG.Profile.the_user_clicks_on_nutritional_drinks()"},"name":"the user clicks on Nutritional Drinks","result":{"duration":4111601800,"status":"passed"}},{"keyword":"And ","line":28,"match":{"location":"com.stepDefinitionTestNG.Profile.the_user_clicks_on_sports_nutrition()"},"name":"the user clicks on Sports Nutrition","result":{"duration":4206887200,"status":"passed"}},{"keyword":"Then ","line":29,"match":{"location":"com.stepDefinitionTestNG.Profile.the_user_verifies_the_sports_nutrition_page_is_displayed()"},"name":"the user verifies the Sports Nutrition page is displayed","result":{"duration":9460400,"status":"passed"}}]},{"start_timestamp":"2025-11-13T09:20:02.001Z","line":42,"id":"shop-by-category-functionality;user-landing-on-search-page;;2","type":"scenario","keyword":"Scenario Outline","name":"User Landing on Search page","description":"","steps":[{"keyword":"Given ","line":33,"match":{"location":"com.stepDefinitionTestNG.Profile.the_user_clicks_on_search_bar()"},"name":"the user clicks on search bar","result":{"duration":2122285000,"status":"passed"}},{"keyword":"When ","line":34,"match":{"location":"com.stepDefinitionTestNG.Profile.the_user_enters_products_from_sheet_and_row(java.lang.Integer,java.lang.Integer)","arguments":[{"val":"0","offset":36},{"val":"0","offset":46}]},"name":"the user enters products from sheet 0 and row 0","result":{"duration":1150913900,"status":"failed","error_message":"java.lang.RuntimeException: Failed to search for product: Boroline\r\n\tat com.pages.HomePage.enterProductInSearchBar(HomePage.java:202)\r\n\tat com.stepDefinitionTestNG.Profile.the_user_enters_products_from_sheet_and_row(Profile.java:251)\r\n\tat ✽.the user enters products from sheet 0 and row 0(file:///C:/Training%20materials/JAVA/Apollo%20247/Apollo247/src/test/resources/Features/Profile.feature:34)\r\nCaused by: org.openqa.selenium.NoSuchElementException: no such element: Unable to locate element: {\"method\":\"xpath\",\"selector\":\"//div[@data-placeholder='Search Medicines']\"}\n  (Session info: chrome=142.0.7444.135)\nFor documentation on this error, please visit: https://www.selenium.dev/documentation/webdriver/troubleshooting/errors#no-such-element-exception\nBuild info: version: '4.34.0', revision: '707dcb4246*'\nSystem info: os.name: 'Windows 11', os.arch: 'amd64', os.version: '10.0', java.version: '23.0.2'\nDriver info: org.openqa.selenium.chrome.ChromeDriver\nCommand: [93684d7e2c4ac5ad2053aefc7b4153f1, findElement {using=xpath, value=//div[@data-placeholder='Search Medicines']}]\nCapabilities {acceptInsecureCerts: false, browserName: chrome, browserVersion: 142.0.7444.135, chrome: {chromedriverVersion: 141.0.7390.78 (2b53b0e231fc..., userDataDir: C:\\Users\\vemulaa\\AppData\\Lo...}, fedcm:accounts: true, goog:chromeOptions: {debuggerAddress: localhost:62619}, networkConnectionEnabled: false, pageLoadStrategy: normal, platformName: windows, proxy: Proxy(), se:cdp: ws://localhost:62619/devtoo..., se:cdpVersion: 142.0.7444.135, setWindowRect: true, strictFileInteractability: false, timeouts: {implicit: 0, pageLoad: 300000, script: 30000}, unhandledPromptBehavior: dismiss and notify, webauthn:extension:credBlob: true, webauthn:extension:largeBlob: true, webauthn:extension:minPinLength: true, webauthn:extension:prf: true, webauthn:virtualAuthenticators: true}\nSession ID: 93684d7e2c4ac5ad2053aefc7b4153f1\r\n\tat java.base/jdk.internal.reflect.DirectConstructorHandleAccessor.newInstance(DirectConstructorHandleAccessor.java:62)\r\n\tat java.base/java.lang.reflect.Constructor.newInstanceWithCaller(Constructor.java:501)\r\n\tat java.base/java.lang.reflect.Constructor.newInstance(Constructor.java:485)\r\n\tat org.openqa.selenium.remote.ErrorCodec.decode(ErrorCodec.java:167)\r\n\tat org.openqa.selenium.remote.codec.w3c.W3CHttpResponseCodec.decode(W3CHttpResponseCodec.java:138)\r\n\tat org.openqa.selenium.remote.codec.w3c.W3CHttpResponseCodec.decode(W3CHttpResponseCodec.java:50)\r\n\tat org.openqa.selenium.remote.HttpCommandExecutor.execute(HttpCommandExecutor.java:215)\r\n\tat org.openqa.selenium.remote.service.DriverCommandExecutor.invokeExecute(DriverCommandExecutor.java:216)\r\n\tat org.openqa.selenium.remote.service.DriverCommandExecutor.execute(DriverCommandExecutor.java:174)\r\n\tat org.openqa.selenium.remote.RemoteWebDriver.execute(RemoteWebDriver.java:544)\r\n\tat org.openqa.selenium.remote.ElementLocation$ElementFinder$2.findElement(ElementLocation.java:165)\r\n\tat org.openqa.selenium.remote.ElementLocation.findElement(ElementLocation.java:59)\r\n\tat org.openqa.selenium.remote.RemoteWebDriver.findElement(RemoteWebDriver.java:367)\r\n\tat org.openqa.selenium.remote.RemoteWebDriver.findElement(RemoteWebDriver.java:361)\r\n\tat org.openqa.selenium.support.pagefactory.DefaultElementLocator.findElement(DefaultElementLocator.java:68)\r\n\tat org.openqa.selenium.support.pagefactory.internal.LocatingElementHandler.invoke(LocatingElementHandler.java:38)\r\n\tat jdk.proxy2/jdk.proxy2.$Proxy22.clear(Unknown Source)\r\n\tat com.pages.HomePage.enterProductInSearchBar(HomePage.java:197)\r\n\t... 2 more\r\n"}},{"keyword":"And ","line":35,"match":{"location":"com.stepDefinitionTestNG.Profile.the_user_clicks_on_health_condition()"},"name":"the user clicks on Health condition","result":{"status":"skipped"}},{"keyword":"Then ","line":36,"match":{"location":"com.stepDefinitionTestNG.Profile.the_user_verifies_the_health_condition_page_is_displayed()"},"name":"the user Verifies the Health condition page is displayed","result":{"duration":996400,"status":"skipped"}}]},{"start_timestamp":"2025-11-13T09:20:05.297Z","line":43,"id":"shop-by-category-functionality;user-landing-on-search-page;;3","type":"scenario","keyword":"Scenario Outline","name":"User Landing on Search page","description":"","steps":[{"keyword":"Given ","line":33,"match":{"location":"com.stepDefinitionTestNG.Profile.the_user_clicks_on_search_bar()"},"name":"the user clicks on search bar","result":{"duration":33498100,"status":"failed","error_message":"org.openqa.selenium.NoSuchElementException: no such element: Unable to locate element: {\"method\":\"xpath\",\"selector\":\"//div[@data-placeholder='Search Medicines']\"}\n  (Session info: chrome=142.0.7444.135)\nFor documentation on this error, please visit: https://www.selenium.dev/documentation/webdriver/troubleshooting/errors#no-such-element-exception\nBuild info: version: '4.34.0', revision: '707dcb4246*'\nSystem info: os.name: 'Windows 11', os.arch: 'amd64', os.version: '10.0', java.version: '23.0.2'\nDriver info: org.openqa.selenium.chrome.ChromeDriver\nCommand: [93684d7e2c4ac5ad2053aefc7b4153f1, findElement {using=xpath, value=//div[@data-placeholder='Search Medicines']}]\nCapabilities {acceptInsecureCerts: false, browserName: chrome, browserVersion: 142.0.7444.135, chrome: {chromedriverVersion: 141.0.7390.78 (2b53b0e231fc..., userDataDir: C:\\Users\\vemulaa\\AppData\\Lo...}, fedcm:accounts: true, goog:chromeOptions: {debuggerAddress: localhost:62619}, networkConnectionEnabled: false, pageLoadStrategy: normal, platformName: windows, proxy: Proxy(), se:cdp: ws://localhost:62619/devtoo..., se:cdpVersion: 142.0.7444.135, setWindowRect: true, strictFileInteractability: false, timeouts: {implicit: 0, pageLoad: 300000, script: 30000}, unhandledPromptBehavior: dismiss and notify, webauthn:extension:credBlob: true, webauthn:extension:largeBlob: true, webauthn:extension:minPinLength: true, webauthn:extension:prf: true, webauthn:virtualAuthenticators: true}\nSession ID: 93684d7e2c4ac5ad2053aefc7b4153f1\r\n\tat java.base/jdk.internal.reflect.DirectConstructorHandleAccessor.newInstance(DirectConstructorHandleAccessor.java:62)\r\n\tat java.base/java.lang.reflect.Constructor.newInstanceWithCaller(Constructor.java:501)\r\n\tat java.base/java.lang.reflect.Constructor.newInstance(Constructor.java:485)\r\n\tat org.openqa.selenium.remote.ErrorCodec.decode(ErrorCodec.java:167)\r\n\tat org.openqa.selenium.remote.codec.w3c.W3CHttpResponseCodec.decode(W3CHttpResponseCodec.java:138)\r\n\tat org.openqa.selenium.remote.codec.w3c.W3CHttpResponseCodec.decode(W3CHttpResponseCodec.java:50)\r\n\tat org.openqa.selenium.remote.HttpCommandExecutor.execute(HttpCommandExecutor.java:215)\r\n\tat org.openqa.selenium.remote.service.DriverCommandExecutor.invokeExecute(DriverCommandExecutor.java:216)\r\n\tat org.openqa.selenium.remote.service.DriverCommandExecutor.execute(DriverCommandExecutor.java:174)\r\n\tat org.openqa.selenium.remote.RemoteWebDriver.execute(RemoteWebDriver.java:544)\r\n\tat org.openqa.selenium.remote.ElementLocation$ElementFinder$2.findElement(ElementLocation.java:165)\r\n\tat org.openqa.selenium.remote.ElementLocation.findElement(ElementLocation.java:59)\r\n\tat org.openqa.selenium.remote.RemoteWebDriver.findElement(RemoteWebDriver.java:367)\r\n\tat org.openqa.selenium.remote.RemoteWebDriver.findElement(RemoteWebDriver.java:361)\r\n\tat org.openqa.selenium.support.pagefactory.DefaultElementLocator.findElement(DefaultElementLocator.java:68)\r\n\tat org.openqa.selenium.support.pagefactory.internal.LocatingElementHandler.invoke(LocatingElementHandler.java:38)\r\n\tat jdk.proxy2/jdk.proxy2.$Proxy22.getWrappedElement(Unknown Source)\r\n\tat org.openqa.selenium.remote.WebElementToJsonConverter.apply(WebElementToJsonConverter.java:48)\r\n\tat java.base/java.util.stream.ReferencePipeline$3$1.accept(ReferencePipeline.java:215)\r\n\tat java.base/java.util.Spliterators$ArraySpliterator.forEachRemaining(Spliterators.java:1024)\r\n\tat java.base/java.util.stream.AbstractPipeline.copyInto(AbstractPipeline.java:570)\r\n\tat java.base/java.util.stream.AbstractPipeline.wrapAndCopyInto(AbstractPipeline.java:560)\r\n\tat java.base/java.util.stream.ReduceOps$ReduceOp.evaluateSequential(ReduceOps.java:921)\r\n\tat java.base/java.util.stream.AbstractPipeline.evaluate(AbstractPipeline.java:265)\r\n\tat java.base/java.util.stream.ReferencePipeline.collect(ReferencePipeline.java:727)\r\n\tat org.openqa.selenium.remote.RemoteWebDriver.executeScript(RemoteWebDriver.java:473)\r\n\tat com.pages.HomePage.clickSearchBar(HomePage.java:189)\r\n\tat com.stepDefinitionTestNG.Profile.the_user_clicks_on_search_bar(Profile.java:208)\r\n\tat ✽.the user clicks on search bar(file:///C:/Training%20materials/JAVA/Apollo%20247/Apollo247/src/test/resources/Features/Profile.feature:33)\r\n"}},{"keyword":"When ","line":34,"match":{"location":"com.stepDefinitionTestNG.Profile.the_user_enters_products_from_sheet_and_row(java.lang.Integer,java.lang.Integer)","arguments":[{"val":"0","offset":36},{"val":"1","offset":46}]},"name":"the user enters products from sheet 0 and row 1","result":{"status":"skipped"}},{"keyword":"And ","line":35,"match":{"location":"com.stepDefinitionTestNG.Profile.the_user_clicks_on_health_condition()"},"name":"the user clicks on Health condition","result":{"status":"skipped"}},{"keyword":"Then ","line":36,"match":{"location":"com.stepDefinitionTestNG.Profile.the_user_verifies_the_health_condition_page_is_displayed()"},"name":"the user Verifies the Health condition page is displayed","result":{"duration":996200,"status":"skipped"}}]}],"tags":[]}]